nb_cli_plugin_bootstrap-0.5.2.dist-info/METADATA
nb_cli_plugin_bootstrap-0.5.2.dist-info/WHEEL
nb_cli_plugin_bootstrap-0.5.2.dist-info/entry_points.txt
nb_cli_plugin_bootstrap-0.5.2.dist-info/licenses/LICENSE
nb_cli_plugin_bootstrap/__init__.py
nb_cli_plugin_bootstrap/const.py
nb_cli_plugin_bootstrap/handlers/__init__.py
nb_cli_plugin_bootstrap/handlers/bootstrap.py
nb_cli_plugin_bootstrap/handlers/pip_index.py
nb_cli_plugin_bootstrap/handlers/shell.py
nb_cli_plugin_bootstrap/handlers/update_project.py
nb_cli_plugin_bootstrap/handlers/venv.py
nb_cli_plugin_bootstrap/plugin.py
nb_cli_plugin_bootstrap/templates/bootstrap/cookiecutter.json
nb_cli_plugin_bootstrap/templates/bootstrap/hooks/post_gen_project.py
nb_cli_plugin_bootstrap/templates/bootstrap/hooks/pre_gen_project.py
nb_cli_plugin_bootstrap/templates/bootstrap/{{cookiecutter.nonebot.folder_name}}/#启动.bat
nb_cli_plugin_bootstrap/templates/bootstrap/{{cookiecutter.nonebot.folder_name}}/#更新所有插件.bat
nb_cli_plugin_bootstrap/templates/bootstrap/{{cookiecutter.nonebot.folder_name}}/#进入虚拟环境.bat
nb_cli_plugin_bootstrap/templates/bootstrap/{{cookiecutter.nonebot.folder_name}}/.env.prod
nb_cli_plugin_bootstrap/templates/bootstrap/{{cookiecutter.nonebot.folder_name}}/bot.py
nb_cli_plugin_bootstrap/templates/bootstrap/{{cookiecutter.nonebot.folder_name}}/pyproject.toml
nb_cli_plugin_bootstrap/templates/bootstrap/{{cookiecutter.nonebot.folder_name}}/src/plugins/ping.py
nb_cli_plugin_bootstrap/utils.py
nb_cli_plugin_bootstrap-0.5.2.dist-info/RECORD
