Metadata-Version: 2.1
Name: nb-cli-plugin-bootstrap
Version: 0.5.2
Summary: A nb-cli plugin for quickly create and bootstrap a NoneBot2 project.
Author-Email: LgCookie <lgc2333@126.com>
License: MIT
Project-URL: homepage, https://github.com/lgc-NB2Dev/nb-cli-plugin-bootstrap
Requires-Python: <4.0,>=3.9
Requires-Dist: nb-cli>=1.4.2
Requires-Dist: shellingham>=1.5.4
Requires-Dist: findpython>=0.6.2
Requires-Dist: cookit[pydantic]>=0.9.3
